complexeva/__init__.py
complexeva/validate.py
complexeva/sequence/__init__.py
complexeva/sequence/compression.py
complexeva/sequence/higuchi.py
complexeva/sequence/lempel_ziv.py
complexeva/sequence/lyapunov_exponent.py
complexeva-0.2.3.dist-info/METADATA
complexeva-0.2.3.dist-info/WHEEL
complexeva-0.2.3.dist-info/top_level.txt
complexeva-0.2.3.dist-info/RECORD
