Metadata-Version: 2.4
Name: complexeva
Version: 0.2.3
Home-page: 
Author: Don Yin
Author-email: don_yin@outlook.com
Dynamic: author
Dynamic: author-email
Dynamic: description
Dynamic: description-content-type
